fastmcp_agents/library/agent/github/__init__.py
fastmcp_agents/library/agent/github/gather_background.py
fastmcp_agents/library/agent/github/investigate_issue.py
fastmcp_agents/library/agent/github/respond_to_issue.py
fastmcp_agents/library/agent/github/shared/git.py
fastmcp_agents/library/agent/github/shared/helpers.py
fastmcp_agents/library/agent/github/shared/logging.py
fastmcp_agents/library/agent/github/shared/mcp.py
fastmcp_agents/library/agent/github/shared/prompts.py
fastmcp_agents_library_agent_github-0.5.7.dist-info/WHEEL
fastmcp_agents_library_agent_github-0.5.7.dist-info/entry_points.txt
fastmcp_agents_library_agent_github-0.5.7.dist-info/METADATA
fastmcp_agents_library_agent_github-0.5.7.dist-info/RECORD
