Metadata-Version: 2.3
Name: fastmcp-agents-library-agent-github
Version: 0.5.7
Summary: Agents for GitHub
Requires-Dist: asyncstdlib>=3.13.1
Requires-Dist: fastmcp-agents-library-agent-simple-code
Requires-Dist: fastmcp-agents-library-mcp
Requires-Dist: fastmcp-ai-agent-bridge-pydantic-ai>=0.1.2
Requires-Dist: gitpython>=3.1.44
Requires-Python: >=3.13
